karoloke/__init__.py
karoloke/backgrounds/__init__.py
karoloke/backgrounds/bg_1.png
karoloke/backgrounds/bg_10.png
karoloke/backgrounds/bg_11.png
karoloke/backgrounds/bg_12.png
karoloke/backgrounds/bg_13.png
karoloke/backgrounds/bg_14.png
karoloke/backgrounds/bg_15.png
karoloke/backgrounds/bg_2.png
karoloke/backgrounds/bg_3.png
karoloke/backgrounds/bg_4.png
karoloke/backgrounds/bg_5.png
karoloke/backgrounds/bg_6.png
karoloke/backgrounds/bg_7.png
karoloke/backgrounds/bg_8.png
karoloke/backgrounds/bg_9.png
karoloke/jukebox_controller.py
karoloke/jukebox_router.py
karoloke/settings.py
karoloke/start_karaoke.py
karoloke/static/__init__.py
karoloke/static/playlist.json
karoloke/static/score_bg_audio.mp3
karoloke/static/setup_icon.png
karoloke/static/singers_icon.png
karoloke/static/spotlight_icon.png
karoloke/templates/__init__.py
karoloke/templates/player.html
karoloke/templates/playlist.html
karoloke/templates/score.html
karoloke/templates/singers.html
karoloke/templates/video_path_setup.html
karoloke/utils.py
karoloke/videos/__init__.py
karoloke-1.2.0.dist-info/METADATA
karoloke-1.2.0.dist-info/WHEEL
karoloke-1.2.0.dist-info/entry_points.txt
karoloke-1.2.0.dist-info/licenses/LICENSE
karoloke-1.2.0.dist-info/RECORD
