Metadata-Version: 2.4
Name: karoloke
Version: 1.2.0
Summary: A simple karaoke framework to your party!
License: MIT
License-File: LICENSE
Author: Antonio Senra
Author-email: acsenrafilho@gmail.com
Requires-Python: >=3.9,<4.0
Classifier: Operating System :: OS Independent
Classifier: Programming Language :: Python :: 3
Classifier: Topic :: Games/Entertainment
Classifier: Topic :: Multimedia :: Video :: Display
Classifier: Topic :: Multimedia :: Sound/Audio :: Players
Classifier: License :: OSI Approved :: MIT License
Requires-Dist: flask (>=3.1.1,<4.0.0)
Requires-Dist: pydantic (>=2.11.7,<3.0.0)
Requires-Dist: python-dotenv (>=1.1.1,<2.0.0)
Requires-Dist: qrcode[pil] (>=8.2,<9.0)
Requires-Dist: rich (>=14.0.0,<15.0.0)
